[
  {
    "title":"Home",
    "url" :"https://www.unacasainarmonia.it/"
  },
  {
    "title":"Chi sono",
    "url" :"/landing"
  },
  {
    "title":"I miei corsi",
    "url" : "https://www.unacasainarmonia.it/courses"
  },
  {
    "title":"I miei servizi",
    "url" :"https://www.unacasainarmonia.it/courses"
  },
  {
    "title":"Masterclass",
    "url" :"https://www.unacasainarmonia.it/"
  },
  {
    "title":"blog",
    "url" :"https://www.unacasainarmonia.it/blog"
  },
  {
    "title":"Contattami",
    "url" :"https://www.unacasainarmonia.it/contattami"
  }
]
